incstorage/__init__.py
incstorage/agent.py
incstorage/engine.py
incstorage/filesystem.py
incstorage/fixbounded.py
incstorage/helpers.py
incstorage/incstorage.py
incstorage/library.py
incstorage/node.py
incstorage/storage.py
incstorage/cli/__init__.py
incstorage/cli/config.py
incstorage/cli/main.py
incstorage/cli/wingdbstub.py
incstorage/cli/workspace.py
incstorage-0.1.2.dist-info/AUTHORS.rst
incstorage-0.1.2.dist-info/LICENSE
incstorage-0.1.2.dist-info/METADATA
incstorage-0.1.2.dist-info/WHEEL
incstorage-0.1.2.dist-info/entry_points.txt
incstorage-0.1.2.dist-info/top_level.txt
incstorage-0.1.2.dist-info/RECORD
