Metadata-Version: 2.1
Name: incstorage
Version: 0.1.2
Summary: Incremental Storage
Home-page: https://github.com/asterio.gonzalez/incstorage
Author: Asterio Gonzalez
Author-email: asterio.gonzalez@gmail.com
License: MIT license
Keywords: incstorage
Classifier: Development Status :: 2 - Pre-Alpha
Classifier: Intended Audience :: Developers
Classifier: License :: OSI Approved :: MIT License
Classifier: Natural Language :: English
Classifier: Programming Language :: Python :: 3
Classifier: Programming Language :: Python :: 3.9
Classifier: Programming Language :: Python :: 3.10
Classifier: Programming Language :: Python :: 3.11
Requires-Python: >=3.6
License-File: LICENSE
License-File: AUTHORS.rst
Requires-Dist: Click >=7.1.2
Requires-Dist: Faker
Requires-Dist: glom
Requires-Dist: jmespath
Requires-Dist: sphinx-autobuild
Requires-Dist: pycelium
Requires-Dist: uswarm >=0.1.1
